<Defs>
	<AlienRace.BackstoryDef Name="BeeAdultBase" Abstract="True">
		<slot>Adulthood</slot>
		<bodyTypeGlobal>Female</bodyTypeGlobal>
		<spawnCategories>
			<li>BeeGeneral</li>
		</spawnCategories>
		<femaleCommonality>100</femaleCommonality>
		<maleCommonality>0</maleCommonality>
	</AlienRace.BackstoryDef>
	<AlienRace.BackstoryDef ParentName="BeeAdultBase">
		<defName>BeeDrudge</defName>
		<title>Drudgery worker</title>
		<titleShort>Drudge</titleShort>
		<baseDesc>Born as a worker under the queen, [PAWN_nameDef] will likely never live to do anything but be that which many will trade for; someone more than capable of dumb labor.</baseDesc>
		<skillGains>
			<li>
				<defName>Plants</defName>
				<amount>4</amount>
			</li>
			<li>
				<defName>Construction</defName>
				<amount>4</amount>
			</li>
		</skillGains>
		<requiredWorkTags>
			<li>ManualDumb</li>
			<li>Cleaning</li>
			<li>Hauling</li>
		</requiredWorkTags>
	</AlienRace.BackstoryDef>
	<AlienRace.BackstoryDef ParentName="BeeAdultBase">
		<defName>BeeAttendant</defName>
		<title>Royal attendant</title>
		<titleShort>Attendant</titleShort>
		<baseDesc>[PAWN_nameDef] was a tireless servant responsible for the caring, cleaning and feeding of the queen.</baseDesc>
		<skillGains>
			<li>
				<defName>Cooking</defName>
				<amount>5</amount>
			</li>
			<li>
				<defName>Medicine</defName>
				<amount>5</amount>
			</li>
			<li>
				<defName>Social</defName>
				<amount>2</amount>
			</li>
		</skillGains>
		<requiredWorkTags>
			<li>Social</li>
			<li>Caring</li>
			<li>Cleaning</li>
		</requiredWorkTags>
	</AlienRace.BackstoryDef>
	<AlienRace.BackstoryDef ParentName="BeeAdultBase">
		<defName>BeeDisgraced</defName>
		<title>Disgraced guard</title>
		<titleShort>Disgraced</titleShort>
		<baseDesc>[PAWN_nameDef] was tasked to protect [PAWN_possessive] queen from danger, but fell from grace after an embarrassing incident involving a pineapple. \nStripped of [PAWN_possessive] position and ashamed, every time [PAWN_nameDef] looks upon a piece of fruit [PAWN_pronoun] is reminded of [PAWN_possessive] failure.</baseDesc>
		<skillGains>
			<!-- what-->
			<li>
				<defName>Shooting</defName>
				<amount>4</amount>
			</li>
			<li>
				<defName>Melee</defName>
				<amount>7</amount>
			</li>
		</skillGains>
		<workDisables>
			<li>PlantWork</li>
		</workDisables>
		<requiredWorkTags>
			<li>Violent</li>
		</requiredWorkTags>
		<disallowedTraits>
			<li>
				<defName>Gourmand</defName>
			</li>
		</disallowedTraits>
	</AlienRace.BackstoryDef>
	<AlienRace.BackstoryDef ParentName="BeeAdultBase">
		<defName>BeeScout</defName>
		<title>Scout</title>
		<titleShort>Scout</titleShort>
		<baseDesc>The long periods spent out of the hive has made [PAWN_nameDef] a resilient individual, well suited to reconnaissance and vanguard work.</baseDesc>
		<maleCommonality>100</maleCommonality>
		<skillGains>
			<li>
				<defName>Plants</defName>
				<amount>3</amount>
			</li>
			<li>
				<defName>Medicine</defName>
				<amount>3</amount>
			</li>
			<li>
				<defName>Shooting</defName>
				<amount>3</amount>
			</li>
		</skillGains>
		<requiredWorkTags>
			<li>Violent</li>
			<li>Animals</li>
		</requiredWorkTags>
		<disallowedTraits>
			<li>
				<defName>Wimp</defName>
			</li>
			<li>
				<defName>Undergrounder</defName>
			</li>
		</disallowedTraits>
	</AlienRace.BackstoryDef>
	<AlienRace.BackstoryDef ParentName="BeeAdultBase">
		<defName>BeeUndertaker</defName>
		<title>Undertaker</title>
		<titleShort>Undertaker</titleShort>
		<baseDesc>[PAWN_nameDef] was responsible for disposing of corpses outside of the hive. This was a thankless yet vital job, lest the dead bodies attract predators.</baseDesc>
		<skillGains>
			<li>
				<defName>Medicine</defName>
				<amount>6</amount>
			</li>
			<li>
				<defName>Animals</defName>
				<amount>6</amount>
			</li>
		</skillGains>
		<requiredWorkTags>
			<li>Hauling</li>
		</requiredWorkTags>
		<workDisables>
			<li>Social</li>
		</workDisables>
	</AlienRace.BackstoryDef>
	<AlienRace.BackstoryDef ParentName="BeeAdultBase">
		<defName>BeeArchitect</defName>
		<title>Honeycomb architect</title>
		<titleShort>Architect</titleShort>
		<baseDesc>Responsible for secreting wax and building the honeycombs, [PAWN_nameDef] would spend most of [PAWN_possessive] time doing exactly that, and only that. Unfortunately, [PAWN_possessive] constant business had left [PAWN_possessive] with little time for socialization or other skills.</baseDesc>
		<skillGains>
			<li>
				<defName>Construction</defName>
				<amount>8</amount>
			</li>
			<li>
				<defName>Crafting</defName>
				<amount>3</amount>
			</li>
		</skillGains>
		<workDisables>
			<li>Social</li>
		</workDisables>
		<requiredWorkTags>
			<li>ManualSkilled</li>
			<li>Crafting</li>
		</requiredWorkTags>
	</AlienRace.BackstoryDef>
	<AlienRace.BackstoryDef ParentName="BeeAdultBase">
		<defName>BeeHiveless</defName>
		<title>Hiveless</title>
		<titleShort>Hiveless</titleShort>
		<baseDesc>[PAWN_nameDef] is without a hive, and without a home. Displaced, [PAWN_pronoun] had to learn to survive on [PAWN_possessive] own. Yet [PAWN_nameDef] also discovered the beauty in everything around [PAWN_possessive].</baseDesc>
		<maleCommonality>100</maleCommonality>
		<skillGains>
			<li>
				<defName>Shooting</defName>
				<amount>4</amount>
			</li>
			<li>
				<defName>Artistic</defName>
				<amount>4</amount>
			</li>
			<li>
				<defName>Medicine</defName>
				<amount>4</amount>
			</li>
		</skillGains>
		<workDisables>
			<li>ManualSkilled</li>
		</workDisables>
		<disallowedTraits>
			<li>
				<defName>Abrasive</defName>
			</li>
			<li>
				<defName>Psychopath</defName>
			</li>
		</disallowedTraits>
	</AlienRace.BackstoryDef>
	<AlienRace.BackstoryDef ParentName="BeeAdultBase">
		<defName>BeeSoldier</defName>
		<title>Veteran soldier</title>
		<titleShort>Soldier</titleShort>
		<baseDesc>Dangerous and lethal, [PAWN_nameDef] is likely the definition of “nope” in many galactic textbooks. However [PAWN_pronoun] has a softer side, dutifully tending [PAWN_possessive] fellow soldiers on the battlefield.</baseDesc>
		<maleCommonality>100</maleCommonality>
		<skillGains>
			<li>
				<defName>Melee</defName>
				<amount>6</amount>
			</li>
			<li>
				<defName>Medicine</defName>
				<amount>4</amount>
			</li>
		</skillGains>
		<requiredWorkTags>
			<li>Violent</li>
			<li>Caring</li>
		</requiredWorkTags>
		<disallowedTraits>
			<li>
				<defName>Wimp</defName>
			</li>
		</disallowedTraits>
	</AlienRace.BackstoryDef>
	<AlienRace.BackstoryDef ParentName="BeeAdultBase">
		<defName>BeePoli</defName>
		<title>Pollen-tician</title>
		<titleShort>Pollen-tician</titleShort>
		<baseDesc>A recent position, made out of spite of the traditional monarchy, [PAWN_nameDef] has become a Pollen-tician, much to the despair of [PAWN_possessive] community</baseDesc>
		<femaleCommonality>50</femaleCommonality>
		<maleCommonality>50</maleCommonality>
		<skillGains>
			<li>
				<defName>Social</defName>
				<amount>10</amount>
			</li>
			<li>
				<defName>Melee</defName>
				<amount>-5</amount>
			</li>
		</skillGains>
		<forcedTraits>
			<li>
				<defName>Greedy</defName>
				<chance>90</chance>
			</li>
		</forcedTraits>
		<requiredWorkTags>
			<li>Social</li>
		</requiredWorkTags>
	</AlienRace.BackstoryDef>
	<AlienRace.BackstoryDef ParentName="BeeAdultBase">
		<defName>BeeNursemaid</defName>
		<title>Nursemaid</title>
		<titleShort>Nursemaid</titleShort>
		<baseDesc>[PAWN_nameDef] cared for the young of the hive.</baseDesc>
		<skillGains>
			<li>
				<defName>Cooking</defName>
				<amount>2</amount>
			</li>
			<li>
				<defName>Social</defName>
				<amount>2</amount>
			</li>
			<li>
				<defName>Medicine</defName>
				<amount>4</amount>
			</li>
			<li>
				<defName>Construction</defName>
				<amount>-5</amount>
			</li>
		</skillGains>
		<requiredWorkTags>
			<li>Caring</li>
			<li>Cleaning</li>
		</requiredWorkTags>
	</AlienRace.BackstoryDef>
</Defs>